[
  {
    "_id": 601,
    "title": "Operating System Fundamentals",
    "description": "Understand the core principles of operating systems including process management, memory management, scheduling, and file systems.",
    "category": ["Operating System Fundamentals",
      "Computer Science",
      "Systems Programming",
      "OS"
    ],
    "tags": {
      "1": [
        "fundamentals of computers",
        "computer architecture",
        "os",
        "operating system"
      ],
      "2": [
        "scheduling",
        "deadlock",
        "cpu",
        "paging",
        "virtual memory"
      ],
      "3": [
        "memory",
        "process",
        "threads",
        "programming"
      ]
    },
    "content": [
      {
        "title": "Lecture 1: Introduction to Operating Systems",
        "videoUrl": "https://videos.edu/os_intro.mp4",
        "pdfPath": "/uploads/os_fundamentals.pdf"
      }
    ],
    "thumbnail": "/uploads/thumb-os.png",
    "createdBy": "user123",
    "date": "2024-09-28T10:00:00",
    "enrolledCount": 400
  },
  {
    "_id": 602,
    "title": "Computer Organization and Architecture",
    "description": "Explore the internal structure of computers, instruction sets, memory hierarchy, pipelining, and I/O systems.",
    "category": ["Computer Organization and Architecture",
    "COA",
    "Computer Organization","Organization and Architecture",
      "Computer Science",
      "Hardware",
      "Systems Design"
    ],
    "tags": {
      "1": [
        "coa",
        "architecture",
        "fundamentals of computers",
        "computer architecture",
        "pipelining",
        "cache",
        "memory"
      ],
      "2": [
        "alu",
        "cpu",
        "control unit",
        "instruction set",
        "registers"
      ],
      "3": [
        "digital electronics",
        "logic"
      ]
    },
    "content": [
      {
        "title": "Lecture 1: Introduction to Computer Architecture",
        "videoUrl": "https://videos.edu/coa_intro.mp4",
        "pdfPath": "/uploads/coa_fundamentals.pdf"
      }
    ],
    "thumbnail": "/uploads/thumb-coa.png",
    "createdBy": "user123",
    "date": "2024-09-28T11:00:00",
    "enrolledCount": 380
  },
  {
    "_id": 603,
    "title": "Formal Language and Automata Theory",
    "description": "Dive into the mathematical foundations of computation, covering automata, regular expressions, grammars, and Turing machines.",
    "category": ["Formal Language and Automata Theory",
    "FLAT",
      "Theoretical CS","Formal Language","Automata Theory",
      "Automata",
      "Mathematics"
    ],
    "tags": {
      "1": [
        "fundamentals of computers",
        "formal methods",
        "state machines"
      ],
      "2": [
        "regex",
        "language theory",
        "compilers",
        "finite state machine"
      ],
      "3": ["automata",
        "dfa",
        "nfa",
        "turing machine",
        "grammar"
        
      ]
    },
    "content": [
      {
        "title": "Lecture 1: Introduction to Automata Theory",
        "videoUrl": "https://videos.edu/automata_intro.mp4",
        "pdfPath": "/uploads/automata_fundamentals.pdf"
      }
    ],
    "thumbnail": "/uploads/thumb-automata.png",
    "createdBy": "user123",
    "date": "2024-09-28T12:00:00",
    "enrolledCount": 350
  },
  {
    "_id": 604,
    "title": "Distributed Systems",
    "description": "Learn how distributed systems work including concepts like replication, consensus, fault tolerance, and consistency models.",
    "category": [
      "System Design","Distributed Systems","DS",
      "Cloud Computing",
      "CS Theory"
    ],
    "tags": {
      "1": ["networks",
        "cloud",
        "fundamentals of computers",
        "distributed"
        
      ],
      "2": [
        "rpc",
        "concurrency",
        "clock synchronization",
        "message passing"
      ],
      "3": [
        "replication",
        "consistency",
        "fault tolerance",
        "nodes"
      ]
    },
    "content": [
      {
        "title": "Lecture 1: Basics of Distributed Computing",
        "videoUrl": "https://videos.edu/distributed_intro.mp4",
        "pdfPath": "/uploads/distributed_systems.pdf"
      }
    ],
    "thumbnail": "/uploads/thumb-distributed.png",
    "createdBy": "user123",
    "date": "2024-09-28T13:00:00",
    "enrolledCount": 360
  },
  {
    "_id": 605,
    "title": "Database Management Systems",
    "description": "Understand how databases work, including relational models, SQL, normalization, transactions, and indexing.",
    "category": [
      "Database",
      "Backend",
      "Information Systems"
    ],
    "tags": {
      "1": [
        "dbms",
        "sql",
        "fundamentals of computers",
        "data modeling",
        "data storage"
      ],
      "2": [
        "indexes",
        "relational",
        "queries",
        "schema",
        "er diagram"
      ],
      "3": [
        "normalization",
        "acid",
        "transactions"
      ]
    },
    "content": [
      {
        "title": "Lecture 1: Introduction to DBMS",
        "videoUrl": "https://videos.edu/dbms_intro.mp4",
        "pdfPath": "/uploads/dbms_fundamentals.pdf"
      }
    ],
    "thumbnail": "/uploads/thumb-dbms.png",
    "createdBy": "user123",
    "date": "2024-09-28T14:00:00",
    "enrolledCount": 420
  },
  {
    "_id": 606,
    "title": "Compiler Design",
    "description": "Learn the phases of compiler construction including lexical analysis, parsing, semantic analysis, and code generation.",
    "category": ["Compiler Design","CD","Compiler",
      "Theoretical CS",
      "Software Design",
      "Programming Languages"
    ],
    "tags": {
      "1": [
        "fundamentals of computers",
        "automata",
        "formal languages"
        
      ],
      "2": [
        "syntax tree",
        "tokenization",
        "semantic analysis",
        "optimization"
      ],
      "3": [
        "compiler",
        "lexer",
        "parser",
        "interpreter",
        "code generation"
      ]
    },
    "content": [
      {
        "title": "Lecture 1: Compiler Structure and Phases",
        "videoUrl": "https://videos.edu/compiler_intro.mp4",
        "pdfPath": "/uploads/compiler_design.pdf"
      }
    ],
    "thumbnail": "/uploads/thumb-compiler.png",
    "createdBy": "user123",
    "date": "2024-09-28T15:00:00",
    "enrolledCount": 340
  },
  {
    "_id": 607,
    "title": "Computer Networks",
    "description": "Explore the foundations of computer networks, including TCP/IP stack, protocols, routing, switching, and network security.",
    "category": ["Computer Networks","Networks","CN",
      "Networking",
      "Systems",
      "Infrastructure"
    ],
    "tags": {
      "1": ["fundamentals of computers",
        "network security",
        "web"
        
      ],
      "2": [
        "ip",
        "udp",
        "firewalls",
        "ethernet",
        "switching",
        "packets"
      ],
      "3": [
        "networks",
        "tcp/ip",
        "osi",
        "http",
        "dns",
        "routing"
      ]
    },
    "content": [
      {
        "title": "Lecture 1: Introduction to Networking",
        "videoUrl": "https://videos.edu/networks_intro.mp4",
        "pdfPath": "/uploads/computer_networks.pdf"
      }
    ],
    "thumbnail": "/uploads/thumb-networks.png",
    "createdBy": "user123",
    "date": "2024-09-28T16:00:00",
    "enrolledCount": 410
  },
  {
    "_id": 608,
    "title": "Object-Oriented Programming (OOPs)",
    "description": "Understand core OOP principles including encapsulation, inheritance, polymorphism, and abstraction with practical examples.",
    "category": ["Object-Oriented Programming (OOPs)","OOPS","Object-Oriented",
      "Programming",
      "Software Engineering",
      "OOP"
    ],
    "tags": {
      "1": ["fundamentals of computers",
        "programming concepts",
        "design"
        
      ],
      "2": [
        "encapsulation",
        "polymorphism",
        "java",
        "c++",
        "python"
      ],
      "3": [
        "oops",
        "class",
        "object",
        "inheritance",
        "abstraction"
      ]
    },
    "content": [
      {
        "title": "Lecture 1: Principles of Object-Oriented Programming",
        "videoUrl": "https://videos.edu/oops_intro.mp4",
        "pdfPath": "/uploads/oops_fundamentals.pdf"
      }
    ],
    "thumbnail": "/uploads/thumb-oops.png",
    "createdBy": "user123",
    "date": "2024-09-28T17:00:00",
    "enrolledCount": 430
  },
  {
    "_id": 609,
    "title": "C Programming Language",
    "description": "Learn the C programming language including syntax, pointers, memory management, structures, and functions.",
    "category": ["c language","C",
      "Programming",
      "Systems",
      "C Language"
    ],
    "tags": {
      "1": ["fundamentals of computers",
        "low-level programming",
        "syntax"
        
      ],
      "2": [
        "memory",
        "data types",
        "structures",
        "input/output",
        "files"
      ],
      "3": [
        "c language",
        "functions",
        "arrays",
        "pointers",
        "loops"
      ]
    },
    "content": [
      {
        "title": "Lecture 1: Basics of C Programming",
        "videoUrl": "https://videos.edu/c_programming_intro.mp4",
        "pdfPath": "/uploads/c_programming_course.pdf"
      }
    ],
    "thumbnail": "/uploads/thumb-c.png",
    "createdBy": "user123",
    "date": "2024-09-28T18:00:00",
    "enrolledCount": 450
  },
  {
    "_id": 610,
    "title": "Microprocessors and Microcontrollers",
    "description": "Learn about the architecture and working of microprocessors and microcontrollers, including instruction sets and interfacing.",
    "category": [
      "Embedded Systems","Microprocessors and Microcontrollers","MPMC","Microprocessors","Microcontrollers",
      "Hardware",
      "Electronics"
    ],
    "tags": {
      "1": ["fundamentals of computers",
        "electronics",
        "digital systems","microprocessor",
        "microcontroller"
        
      ],
      "2": [
        "registers",
        "interrupts",
        "timers",
        "i/o interfacing",
        "memory map"
      ],
      "3": [
        "8085",
        "8051",
        "instructions"
      ]
    },
    "content": [
      {
        "title": "Lecture 1: Introduction to Microprocessors",
        "videoUrl": "https://videos.edu/micro_intro.mp4",
        "pdfPath": "/uploads/microprocessors_course.pdf"
      }
    ],
    "thumbnail": "/uploads/thumb-micro.png",
    "createdBy": "user123",
    "date": "2024-09-28T19:00:00",
    "enrolledCount": 390
  }
]